<?xml version="1.0" encoding="UTF-8"?>
<jcr:root xmlns:sling="http://sling.apache.org/jcr/sling/1.0" xmlns:cq="http://www.day.com/jcr/cq/1.0"
          xmlns:jcr="http://www.jcp.org/jcr/1.0" xmlns:mix="http://www.jcp.org/jcr/mix/1.0"
          xmlns:nt="http://www.jcp.org/jcr/nt/1.0"
          jcr:primaryType="cq:Page">
    <jcr:content
            cq:lastModified="{Date}2022-03-14T23:14:17.035+05:30"
            cq:lastModifiedBy="admin"
            cq:template="/conf/aemgeeks/settings/wcm/templates/page-content"
            jcr:isCheckedOut="{Boolean}true"
            jcr:mixinTypes="[mix:versionable]"
            jcr:primaryType="cq:PageContent"
            jcr:title="speciman"
            jcr:uuid="b608b9ed-73b0-4cf1-a41b-9fcc560c01c8"
            sling:resourceType="aemgeeks/components/page">
        <root
                jcr:primaryType="nt:unstructured"
                sling:resourceType="aemgeeks/components/container"
                layout="responsiveGrid">
            <container
                    jcr:primaryType="nt:unstructured"
                    sling:resourceType="aemgeeks/components/container"
                    layout="responsiveGrid">
                <title
                        jcr:primaryType="nt:unstructured"
                        sling:resourceType="aemgeeks/components/title"/>
                <container
                        jcr:primaryType="nt:unstructured"
                        sling:resourceType="aemgeeks/components/container"
                        layout="responsiveGrid">
                    <helloworld
                            jcr:created="{Date}2022-02-27T02:38:20.961+05:30"
                            jcr:createdBy="admin"
                            jcr:lastModified="{Date}2022-02-27T02:38:20.961+05:30"
                            jcr:lastModifiedBy="admin"
                            jcr:primaryType="nt:unstructured"
                            sling:resourceType="aemgeeks/components/helloworld"/>
                    <global_navigation
                            jcr:created="{Date}2022-03-06T19:45:51.274+05:30"
                            jcr:createdBy="admin"
                            jcr:lastModified="{Date}2022-03-06T22:19:21.277+05:30"
                            jcr:lastModifiedBy="admin"
                            jcr:primaryType="nt:unstructured"
                            sling:resourceType="aemgeeks/components/global-navigation">
                        <continents jcr:primaryType="nt:unstructured">
                            <item0
                                    jcr:primaryType="nt:unstructured"
                                    name="Asia">
                                <countries jcr:primaryType="nt:unstructured">
                                    <item0
                                            jcr:primaryType="nt:unstructured"
                                            code="www.google.com"
                                            name="India"/>
                                    <item1
                                            jcr:primaryType="nt:unstructured"
                                            code="www.linkedin.com"
                                            name="China"/>
                                </countries>
                            </item0>
                            <item1
                                    jcr:primaryType="nt:unstructured"
                                    name="Europe">
                                <countries jcr:primaryType="nt:unstructured">
                                    <item0
                                            jcr:primaryType="nt:unstructured"
                                            code="www.verizon.com"
                                            name="Yukrane"/>
                                    <item1
                                            jcr:primaryType="nt:unstructured"
                                            code="RS"
                                            name="Russia"/>
                                </countries>
                            </item1>
                            <item2
                                    jcr:primaryType="nt:unstructured"
                                    name="Africa"/>
                            <item3
                                    jcr:primaryType="nt:unstructured"
                                    name="Antarctica"/>
                        </continents>
                    </global_navigation>
                    <text
                            jcr:created="{Date}2022-03-14T23:03:25.887+05:30"
                            jcr:createdBy="admin"
                            jcr:lastModified="{Date}2022-03-14T23:03:34.939+05:30"
                            jcr:lastModifiedBy="admin"
                            jcr:primaryType="nt:unstructured"
                            sling:resourceType="aemgeeks/components/text"
                            text="&lt;p>Pavan&lt;/p>&#xa;"
                            textIsRich="true"/>
                    <image
                            jcr:created="{Date}2022-03-14T23:11:43.708+05:30"
                            jcr:createdBy="admin"
                            jcr:lastModified="{Date}2022-03-14T23:11:43.708+05:30"
                            jcr:lastModifiedBy="admin"
                            jcr:primaryType="nt:unstructured"
                            sling:resourceType="aemgeeks/components/image"/>
                    <text_copy
                            jcr:created="{Date}2022-03-14T23:03:25.887+05:30"
                            jcr:createdBy="admin"
                            jcr:lastModified="{Date}2022-03-14T23:13:32.076+05:30"
                            jcr:lastModifiedBy="admin"
                            jcr:primaryType="nt:unstructured"
                            sling:resourceType="aemgeeks/components/text"
                            text="&lt;p>Pavan2&lt;/p>&#xa;"
                            textIsRich="true"/>
                    <text_copy_copy
                            jcr:created="{Date}2022-03-14T23:03:25.887+05:30"
                            jcr:createdBy="admin"
                            jcr:lastModified="{Date}2022-03-14T23:13:37.955+05:30"
                            jcr:lastModifiedBy="admin"
                            jcr:primaryType="nt:unstructured"
                            sling:resourceType="aemgeeks/components/text"
                            text="&lt;p>Pavan3&lt;/p>&#xa;"
                            textIsRich="true"/>
                    <text_1592831508
                            jcr:created="{Date}2022-03-14T23:14:04.126+05:30"
                            jcr:createdBy="admin"
                            jcr:lastModified="{Date}2022-03-14T23:14:17.029+05:30"
                            jcr:lastModifiedBy="admin"
                            jcr:primaryType="nt:unstructured"
                            sling:resourceType="aemgeeks/components/text"
                            text="&lt;p>pavan4&lt;/p>&#xa;"
                            textIsRich="true"/>
                </container>
            </container>
        </root>
    </jcr:content>
</jcr:root>
